math_kit_FF/__init__.py
math_kit_L-0.4.0.dist-info/LICENSE.txt
math_kit_L-0.4.0.dist-info/METADATA
math_kit_L-0.4.0.dist-info/WHEEL
math_kit_L-0.4.0.dist-info/top_level.txt
math_kit_L-0.4.0.dist-info/RECORD
