Metadata-Version: 2.1
Name: math_kit_L
Version: 0.4.0
Home-page: https://github.com/lmcteam206/math_kit_FF/tree/main
Author: lmc
Author-email: lmcteam206@gmail.com
Classifier: Programming Language :: Python :: 3
Classifier: License :: OSI Approved :: MIT License
Classifier: Operating System :: OS Independent
License-File: LICENSE.txt
